LICENSE
README.md
setup.py
src/adk/__init__.py
src/adk/command_list.py
src/adk/command_processor.py
src/adk/decorators.py
src/adk/exceptions.py
src/adk/settings.py
src/adk/type_aliases.py
src/adk/utils.py
src/adk/validators.py
src/adk/version.py
src/adk/api/__init__.py
src/adk/api/local_api.py
src/adk/api/qne_client.py
src/adk/api/remote_api.py
src/adk/generators/__init__.py
src/adk/generators/instruction_generator.py
src/adk/generators/network_generator.py
src/adk/generators/result_generator.py
src/adk/generators/template_generator.py
src/adk/managers/__init__.py
src/adk/managers/auth_manager.py
src/adk/managers/config_manager.py
src/adk/managers/resource_manager.py
src/adk/managers/roundset_manager.py
src/adk/networks/channels.json
src/adk/networks/networks.json
src/adk/networks/nodes.json
src/adk/networks/templates.json
src/adk/parsers/__init__.py
src/adk/parsers/encoders.py
src/adk/parsers/input_parser.py
src/adk/parsers/output_converter.py
src/adk/schema/applications/application.json
src/adk/schema/applications/manifest.json
src/adk/schema/applications/network.json
src/adk/schema/applications/result.json
src/adk/schema/experiments/asset.json
src/adk/schema/experiments/experiment.json
src/adk/schema/networks/channel_asset.json
src/adk/schema/networks/network_asset.json
src/adk/schema/networks/node_asset.json
src/adk/schema/networks/qubit.json
src/adk/schema/networks/roletemplate.json
src/adk/schema/networks/template.json
src/qne_adk.egg-info/PKG-INFO
src/qne_adk.egg-info/SOURCES.txt
src/qne_adk.egg-info/dependency_links.txt
src/qne_adk.egg-info/entry_points.txt
src/qne_adk.egg-info/requires.txt
src/qne_adk.egg-info/top_level.txt