Metadata-Version: 2.1
Name: qne-adk
Version: 0.2.0
Summary: Application Development Kit to interact with the Quantum Network Explorer
Home-page: https://github.com/QuTech-Delft/qne-adk
Author: QuTech-Delft
Author-email: support@quantum-network.com
License: MIT
Platform: UNKNOWN
Classifier: Development Status :: 4 - Beta
Classifier: Environment :: Console
Classifier: Intended Audience :: Developers
Classifier: Intended Audience :: Science/Research
Classifier: License :: OSI Approved :: MIT License
Classifier: Operating System :: MacOS
Classifier: Operating System :: Microsoft :: Windows
Classifier: Operating System :: POSIX :: Linux
Classifier: Programming Language :: Python :: 3
Classifier: Programming Language :: Python :: 3.8
Classifier: Programming Language :: Python :: 3.9
Classifier: Programming Language :: Python :: 3.10
Classifier: Topic :: Scientific/Engineering
Requires-Python: >=3.8
Provides-Extra: dev
Provides-Extra: rtd
License-File: LICENSE
